{
  "articles": [
    {
      "title": "大友愛",
      "views": 257392,
      "rank": 1
    },
    {
      "title": "平賀源内",
      "views": 96660,
      "rank": 2
    },
    {
      "title": "秋本啓之",
      "views": 92210,
      "rank": 3
    },
    {
      "title": "山本辰生",
      "views": 76951,
      "rank": 4
    },
    {
      "title": "市川実日子",
      "views": 64194,
      "rank": 5
    },
    {
      "title": "平岩紙",
      "views": 61912,
      "rank": 6
    },
    {
      "title": "蔦屋重三郎",
      "views": 55261,
      "rank": 7
    },
    {
      "title": "べらぼう〜蔦重栄華乃夢噺〜",
      "views": 49664,
      "rank": 8
    },
    {
      "title": "田沼意次",
      "views": 44474,
      "rank": 9
    },
    {
      "title": "渡邊渚",
      "views": 39819,
      "rank": 10
    },
    {
      "title": "99.9-刑事専門弁護士-THE_MOVIE",
      "views": 36168,
      "rank": 11
    },
    {
      "title": "市川実和子",
      "views": 34157,
      "rank": 12
    },
    {
      "title": "パーフェクト_リバティー教団",
      "views": 33016,
      "rank": 13
    },
    {
      "title": "Mrs._GREEN_APPLE",
      "views": 32093,
      "rank": 14
    },
    {
      "title": "筧美和子",
      "views": 31805,
      "rank": 15
    },
    {
      "title": "99.9-刑事専門弁護士-",
      "views": 31416,
      "rank": 16
    },
    {
      "title": "SAKAMOTO_DAYS",
      "views": 30089,
      "rank": 17
    },
    {
      "title": "上白石萌音",
      "views": 26712,
      "rank": 18
    },
    {
      "title": "小芝風花",
      "views": 24165,
      "rank": 19
    },
    {
      "title": "阿修羅のごとく",
      "views": 23653,
      "rank": 20
    },
    {
      "title": "徳川治済",
      "views": 23170,
      "rank": 21
    },
    {
      "title": "令和ロマン",
      "views": 22280,
      "rank": 22
    },
    {
      "title": "大谷龍太",
      "views": 22169,
      "rank": 23
    },
    {
      "title": "PL学園中学校・高等学校",
      "views": 21763,
      "rank": 24
    },
    {
      "title": "中谷元",
      "views": 21013,
      "rank": 25
    },
    {
      "title": "上白石萌歌",
      "views": 20956,
      "rank": 26
    },
    {
      "title": "松平定信",
      "views": 20409,
      "rank": 27
    },
    {
      "title": "源田壮亮",
      "views": 20318,
      "rank": 28
    },
    {
      "title": "ちゃんみな",
      "views": 20199,
      "rank": 29
    },
    {
      "title": "中居正広",
      "views": 20119,
      "rank": 30
    },
    {
      "title": "安克昌",
      "views": 19969,
      "rank": 31
    },
    {
      "title": "山内総一郎",
      "views": 19821,
      "rank": 32
    },
    {
      "title": "衛藤美彩",
      "views": 19746,
      "rank": 33
    },
    {
      "title": "岡田有希子",
      "views": 19658,
      "rank": 34
    },
    {
      "title": "岩屋毅",
      "views": 19094,
      "rank": 35
    },
    {
      "title": "SMAP解散騒動",
      "views": 18713,
      "rank": 36
    },
    {
      "title": "瀬川菊之丞_(2代目)",
      "views": 18663,
      "rank": 37
    },
    {
      "title": "グリーンランド",
      "views": 18600,
      "rank": 38
    },
    {
      "title": "チ。-地球の運動について-",
      "views": 18320,
      "rank": 39
    },
    {
      "title": "横浜流星",
      "views": 18308,
      "rank": 40
    },
    {
      "title": "風と共に去りぬ",
      "views": 18209,
      "rank": 41
    },
    {
      "title": "徳川家斉",
      "views": 16851,
      "rank": 42
    },
    {
      "title": "倉科カナ",
      "views": 16177,
      "rank": 43
    },
    {
      "title": "広瀬武夫",
      "views": 16092,
      "rank": 44
    },
    {
      "title": "イカゲーム",
      "views": 15856,
      "rank": 45
    },
    {
      "title": "ハウルの動く城",
      "views": 15705,
      "rank": 46
    },
    {
      "title": "薬屋のひとりごと",
      "views": 15572,
      "rank": 47
    },
    {
      "title": "柳生一族の陰謀",
      "views": 15227,
      "rank": 48
    },
    {
      "title": "松坂桃李",
      "views": 14957,
      "rank": 49
    },
    {
      "title": "忠犬立ハチ高",
      "views": 14632,
      "rank": 50
    },
    {
      "title": "蒔田彩珠",
      "views": 14317,
      "rank": 51
    },
    {
      "title": "成人の日",
      "views": 14116,
      "rank": 52
    },
    {
      "title": "瀬川",
      "views": 13723,
      "rank": 53
    },
    {
      "title": "田中希実",
      "views": 13625,
      "rank": 54
    },
    {
      "title": "関水渚",
      "views": 13613,
      "rank": 55
    },
    {
      "title": "瀬川菊之丞",
      "views": 13548,
      "rank": 56
    },
    {
      "title": "新浜レオン",
      "views": 13332,
      "rank": 57
    },
    {
      "title": "川村楓",
      "views": 13303,
      "rank": 58
    },
    {
      "title": "寺田龍平",
      "views": 13210,
      "rank": 59
    },
    {
      "title": "香川照之",
      "views": 13210,
      "rank": 60
    },
    {
      "title": "皇后盃全国都道府県対抗女子駅伝競走大会",
      "views": 13067,
      "rank": 61
    },
    {
      "title": "フォレスト_(テレビドラマ)",
      "views": 13053,
      "rank": 62
    },
    {
      "title": "俺だけレベルアップな件",
      "views": 12895,
      "rank": 63
    },
    {
      "title": "メダリスト_(漫画)",
      "views": 12768,
      "rank": 64
    },
    {
      "title": "四宮ありす",
      "views": 12460,
      "rank": 65
    },
    {
      "title": "佐々木恭子",
      "views": 12259,
      "rank": 66
    },
    {
      "title": "徳川家治",
      "views": 12229,
      "rank": 67
    },
    {
      "title": "赤楚衛二",
      "views": 11880,
      "rank": 68
    },
    {
      "title": "女子高生コンクリート詰め殺人事件",
      "views": 11773,
      "rank": 69
    },
    {
      "title": "MAYA_MAXX",
      "views": 11746,
      "rank": 70
    },
    {
      "title": "中嶋優一",
      "views": 11657,
      "rank": 71
    },
    {
      "title": "大森元貴",
      "views": 11597,
      "rank": 72
    },
    {
      "title": "杉咲花",
      "views": 11583,
      "rank": 73
    },
    {
      "title": "原菜乃華",
      "views": 11559,
      "rank": 74
    },
    {
      "title": "不破聖衣来",
      "views": 11437,
      "rank": 75
    },
    {
      "title": "ホットスポット_(テレビドラマ)",
      "views": 11124,
      "rank": 76
    },
    {
      "title": "森下佳子",
      "views": 11123,
      "rank": 77
    },
    {
      "title": "大谷翔平",
      "views": 11089,
      "rank": 78
    },
    {
      "title": "上原浩治",
      "views": 11035,
      "rank": 79
    },
    {
      "title": "心の傷を癒すということ_(テレビドラマ)",
      "views": 10915,
      "rank": 80
    },
    {
      "title": "清野菜名",
      "views": 10910,
      "rank": 81
    },
    {
      "title": "風と共に去りぬ_(映画)",
      "views": 10845,
      "rank": 82
    },
    {
      "title": "水島諸島",
      "views": 10722,
      "rank": 83
    },
    {
      "title": "長塚京三",
      "views": 10678,
      "rank": 84
    },
    {
      "title": "舟越保武",
      "views": 10542,
      "rank": 85
    },
    {
      "title": "比嘉愛未",
      "views": 10342,
      "rank": 86
    },
    {
      "title": "中村隼人_(歌舞伎役者)",
      "views": 10330,
      "rank": 87
    },
    {
      "title": "狩野舞子",
      "views": 10284,
      "rank": 88
    },
    {
      "title": "大畑大介",
      "views": 10199,
      "rank": 89
    },
    {
      "title": "土田一徳",
      "views": 10166,
      "rank": 90
    },
    {
      "title": "松重豊",
      "views": 10150,
      "rank": 91
    },
    {
      "title": "田中公平",
      "views": 10114,
      "rank": 92
    },
    {
      "title": "CUTIE_STREET",
      "views": 10083,
      "rank": 93
    },
    {
      "title": "グランメゾン東京",
      "views": 10004,
      "rank": 94
    },
    {
      "title": "石田健",
      "views": 9955,
      "rank": 95
    },
    {
      "title": "山田姫奈",
      "views": 9907,
      "rank": 96
    },
    {
      "title": "坂の上の雲_(テレビドラマ)",
      "views": 9850,
      "rank": 97
    },
    {
      "title": "魔法つかいプリキュア!",
      "views": 9845,
      "rank": 98
    },
    {
      "title": "藤岡弘、",
      "views": 9739,
      "rank": 99
    },
    {
      "title": "廣中璃梨佳",
      "views": 9720,
      "rank": 100
    },
    {
      "title": "薬屋のひとりごと_(アニメ)",
      "views": 9619,
      "rank": 101
    },
    {
      "title": "岡田武史",
      "views": 9527,
      "rank": 102
    },
    {
      "title": "長谷川宣以",
      "views": 9524,
      "rank": 103
    },
    {
      "title": "平子理沙",
      "views": 9510,
      "rank": 104
    },
    {
      "title": "徳川家重",
      "views": 9486,
      "rank": 105
    },
    {
      "title": "田中美奈子",
      "views": 9417,
      "rank": 106
    },
    {
      "title": "宮村優子_(声優)",
      "views": 9415,
      "rank": 107
    },
    {
      "title": "ヴィヴィアン・リー",
      "views": 9390,
      "rank": 108
    },
    {
      "title": "爆上戦隊ブンブンジャー",
      "views": 9380,
      "rank": 109
    },
    {
      "title": "ドルーリー朱瑛里",
      "views": 9366,
      "rank": 110
    },
    {
      "title": "鈴木祐斗",
      "views": 9351,
      "rank": 111
    },
    {
      "title": "西村賢太",
      "views": 9225,
      "rank": 112
    },
    {
      "title": "松平武元",
      "views": 9054,
      "rank": 113
    },
    {
      "title": "寺尾常史",
      "views": 8991,
      "rank": 114
    },
    {
      "title": "瀬戸朝香",
      "views": 8945,
      "rank": 115
    },
    {
      "title": "岡田太郎",
      "views": 8851,
      "rank": 116
    },
    {
      "title": "瀬戸環奈",
      "views": 8812,
      "rank": 117
    },
    {
      "title": "にゃんこスター",
      "views": 8771,
      "rank": 118
    },
    {
      "title": "魔神創造伝ワタル",
      "views": 8764,
      "rank": 119
    },
    {
      "title": "No_No_Girls",
      "views": 8679,
      "rank": 120
    },
    {
      "title": "FRUITS_ZIPPER",
      "views": 8670,
      "rank": 121
    },
    {
      "title": "木村拓哉",
      "views": 8449,
      "rank": 122
    },
    {
      "title": "孤独のグルメ_(テレビドラマ)",
      "views": 8397,
      "rank": 123
    },
    {
      "title": "吉岡里帆",
      "views": 8366,
      "rank": 124
    },
    {
      "title": "ダンダダン",
      "views": 8319,
      "rank": 125
    },
    {
      "title": "SHOGUN_将軍",
      "views": 8288,
      "rank": 126
    },
    {
      "title": "地縛少年花子くん",
      "views": 8178,
      "rank": 127
    },
    {
      "title": "桐山照史",
      "views": 8146,
      "rank": 128
    },
    {
      "title": "新井素子",
      "views": 8098,
      "rank": 129
    },
    {
      "title": "「天久鷹央」シリーズ",
      "views": 8081,
      "rank": 130
    },
    {
      "title": "宮島咲良",
      "views": 8030,
      "rank": 131
    },
    {
      "title": "こっちのけんと",
      "views": 7879,
      "rank": 132
    },
    {
      "title": "ミステリと言う勿れ",
      "views": 7867,
      "rank": 133
    },
    {
      "title": "魔神英雄伝ワタル",
      "views": 7812,
      "rank": 134
    },
    {
      "title": "田浦英理歌",
      "views": 7790,
      "rank": 135
    },
    {
      "title": "吉沢亮",
      "views": 7729,
      "rank": 136
    },
    {
      "title": "B'z",
      "views": 7657,
      "rank": 137
    },
    {
      "title": "吉原_(東京都)",
      "views": 7642,
      "rank": 138
    },
    {
      "title": "駿台学園中学校・高等学校",
      "views": 7623,
      "rank": 139
    },
    {
      "title": "成人式",
      "views": 7548,
      "rank": 140
    },
    {
      "title": "鈴木亮平_(俳優)",
      "views": 7547,
      "rank": 141
    },
    {
      "title": "ハリウッドザコシショウ",
      "views": 7547,
      "rank": 142
    },
    {
      "title": "Snow_Man",
      "views": 7507,
      "rank": 143
    },
    {
      "title": "ババンババンバンバンパイア",
      "views": 7481,
      "rank": 144
    },
    {
      "title": "小林祐梨子",
      "views": 7449,
      "rank": 145
    },
    {
      "title": "松本若菜",
      "views": 7400,
      "rank": 146
    },
    {
      "title": "共栄学園中学高等学校",
      "views": 7373,
      "rank": 147
    },
    {
      "title": "Travis_Japan",
      "views": 7365,
      "rank": 148
    },
    {
      "title": "膳場貴子",
      "views": 7259,
      "rank": 149
    },
    {
      "title": "沖縄リゾート_コンシェルジュ具志堅陽子の名推理",
      "views": 7081,
      "rank": 150
    },
    {
      "title": "和田明日香",
      "views": 6995,
      "rank": 151
    },
    {
      "title": "童門冬二",
      "views": 6992,
      "rank": 152
    },
    {
      "title": "玉城ティナ",
      "views": 6951,
      "rank": 153
    },
    {
      "title": "稲葉浩志",
      "views": 6895,
      "rank": 154
    },
    {
      "title": "愛希れいか",
      "views": 6870,
      "rank": 155
    },
    {
      "title": "錦織圭",
      "views": 6825,
      "rank": 156
    },
    {
      "title": "菊池風磨",
      "views": 6821,
      "rank": 157
    },
    {
      "title": "マミーマート",
      "views": 6754,
      "rank": 158
    },
    {
      "title": "堺正章",
      "views": 6749,
      "rank": 159
    },
    {
      "title": "鈴木杏",
      "views": 6738,
      "rank": 160
    },
    {
      "title": "小野花梨",
      "views": 6699,
      "rank": 161
    },
    {
      "title": "ロバート・オッペンハイマー",
      "views": 6687,
      "rank": 162
    },
    {
      "title": "ユーベルブラット",
      "views": 6604,
      "rank": 163
    },
    {
      "title": "カーネーション_(テレビドラマ)",
      "views": 6584,
      "rank": 164
    },
    {
      "title": "悪役令嬢転生おじさん",
      "views": 6530,
      "rank": 165
    },
    {
      "title": "畑芽育",
      "views": 6525,
      "rank": 166
    },
    {
      "title": "日本",
      "views": 6480,
      "rank": 167
    },
    {
      "title": "江藤名保子",
      "views": 6469,
      "rank": 168
    },
    {
      "title": "菅田将暉",
      "views": 6466,
      "rank": 169
    },
    {
      "title": "安田顕",
      "views": 6418,
      "rank": 170
    },
    {
      "title": "全修。",
      "views": 6413,
      "rank": 171
    },
    {
      "title": "石原由希",
      "views": 6408,
      "rank": 172
    },
    {
      "title": "小林良平",
      "views": 6367,
      "rank": 173
    },
    {
      "title": "FANZA",
      "views": 6223,
      "rank": 174
    },
    {
      "title": "積水ハウス地面師詐欺事件",
      "views": 6222,
      "rank": 175
    },
    {
      "title": "徳川吉宗",
      "views": 6218,
      "rank": 176
    },
    {
      "title": "ILiFE!",
      "views": 6159,
      "rank": 177
    },
    {
      "title": "1月12日",
      "views": 6101,
      "rank": 178
    },
    {
      "title": "悪魔のいけにえ",
      "views": 6098,
      "rank": 179
    },
    {
      "title": "大泉洋",
      "views": 6079,
      "rank": 180
    },
    {
      "title": "木村沙織",
      "views": 6026,
      "rank": 181
    },
    {
      "title": "花束みたいな恋をした",
      "views": 6018,
      "rank": 182
    },
    {
      "title": "岩田剛典",
      "views": 6005,
      "rank": 183
    },
    {
      "title": "黒姫伝説",
      "views": 5917,
      "rank": 184
    },
    {
      "title": "対馬丸",
      "views": 5902,
      "rank": 185
    },
    {
      "title": "ワイドナショー",
      "views": 5899,
      "rank": 186
    },
    {
      "title": "阪神・淡路大震災",
      "views": 5845,
      "rank": 187
    },
    {
      "title": "シャングリラ・フロンティア〜クソゲーハンター、神ゲーに挑まんとす〜",
      "views": 5822,
      "rank": 188
    },
    {
      "title": "KinKi_Kids",
      "views": 5781,
      "rank": 189
    },
    {
      "title": "MIYAVI",
      "views": 5767,
      "rank": 190
    },
    {
      "title": "尾野真千子",
      "views": 5744,
      "rank": 191
    },
    {
      "title": "地面師たち",
      "views": 5707,
      "rank": 192
    },
    {
      "title": "森香澄",
      "views": 5692,
      "rank": 193
    },
    {
      "title": "目黒蓮",
      "views": 5683,
      "rank": 194
    },
    {
      "title": "花魁",
      "views": 5681,
      "rank": 195
    },
    {
      "title": "BABYMONSTER",
      "views": 5677,
      "rank": 196
    },
    {
      "title": "御木貴日止",
      "views": 5676,
      "rank": 197
    },
    {
      "title": "沖縄で好きになった子が方言すぎてツラすぎる",
      "views": 5676,
      "rank": 198
    },
    {
      "title": "芦田愛菜",
      "views": 5674,
      "rank": 199
    },
    {
      "title": "日高光啓",
      "views": 5653,
      "rank": 200
    },
    {
      "title": "スキップとローファー",
      "views": 5648,
      "rank": 201
    },
    {
      "title": "加藤ミリヤ",
      "views": 5633,
      "rank": 202
    },
    {
      "title": "亀田製菓",
      "views": 5623,
      "rank": 203
    },
    {
      "title": "大山加奈",
      "views": 5597,
      "rank": 204
    },
    {
      "title": "黒岩メダカに私の可愛いが通じない",
      "views": 5594,
      "rank": 205
    },
    {
      "title": "香取慎吾",
      "views": 5589,
      "rank": 206
    },
    {
      "title": "さや香",
      "views": 5578,
      "rank": 207
    },
    {
      "title": "Vaundy",
      "views": 5569,
      "rank": 208
    },
    {
      "title": "藤かんな",
      "views": 5567,
      "rank": 209
    },
    {
      "title": "小林公太",
      "views": 5548,
      "rank": 210
    },
    {
      "title": "Dr.STONE",
      "views": 5529,
      "rank": 211
    },
    {
      "title": "真也加ステファン",
      "views": 5528,
      "rank": 212
    },
    {
      "title": "戸田恵梨香",
      "views": 5506,
      "rank": 213
    },
    {
      "title": "忍たま乱太郎",
      "views": 5477,
      "rank": 214
    },
    {
      "title": "火病",
      "views": 5463,
      "rank": 215
    },
    {
      "title": "ギルドの受付嬢ですが、残業は嫌なのでボスをソロ討伐しようと思います",
      "views": 5462,
      "rank": 216
    },
    {
      "title": "プライベートバンカー_(テレビドラマ)",
      "views": 5442,
      "rank": 217
    },
    {
      "title": "クラーク・ゲーブル",
      "views": 5439,
      "rank": 218
    },
    {
      "title": "戦隊レッド_異世界で冒険者になる",
      "views": 5420,
      "rank": 219
    },
    {
      "title": "ちゃんぴおんず",
      "views": 5391,
      "rank": 220
    },
    {
      "title": "石破茂",
      "views": 5382,
      "rank": 221
    },
    {
      "title": "【推しの子】",
      "views": 5373,
      "rank": 222
    },
    {
      "title": "井之脇海",
      "views": 5371,
      "rank": 223
    },
    {
      "title": "長井秀和",
      "views": 5365,
      "rank": 224
    },
    {
      "title": "ガリレオ_(テレビドラマ)",
      "views": 5363,
      "rank": 225
    },
    {
      "title": "となりのナースエイド",
      "views": 5362,
      "rank": 226
    },
    {
      "title": "大塚剛央",
      "views": 5361,
      "rank": 227
    },
    {
      "title": "実践学園中学・高等学校",
      "views": 5350,
      "rank": 228
    },
    {
      "title": "琴櫻将傑",
      "views": 5341,
      "rank": 229
    },
    {
      "title": "十角館の殺人",
      "views": 5341,
      "rank": 230
    },
    {
      "title": "スーパー戦隊シリーズ",
      "views": 5338,
      "rank": 231
    },
    {
      "title": "旅順港閉塞作戦",
      "views": 5313,
      "rank": 232
    },
    {
      "title": "ターミネーター3",
      "views": 5305,
      "rank": 233
    },
    {
      "title": "Aランクパーティを離脱した俺は、元教え子たちと迷宮深部を目指す。",
      "views": 5301,
      "rank": 234
    },
    {
      "title": "性行為",
      "views": 5297,
      "rank": 235
    },
    {
      "title": "生田斗真",
      "views": 5285,
      "rank": 236
    },
    {
      "title": "宮近海斗",
      "views": 5277,
      "rank": 237
    },
    {
      "title": "川栄李奈",
      "views": 5256,
      "rank": 238
    },
    {
      "title": "河合優実",
      "views": 5240,
      "rank": 239
    },
    {
      "title": "琴風豪規",
      "views": 5231,
      "rank": 240
    },
    {
      "title": "髙橋藍",
      "views": 5230,
      "rank": 241
    },
    {
      "title": "ラランド_(お笑いコンビ)",
      "views": 5228,
      "rank": 242
    },
    {
      "title": "二宮和也",
      "views": 5214,
      "rank": 243
    },
    {
      "title": "デヴィ・スカルノ",
      "views": 5191,
      "rank": 244
    },
    {
      "title": "SUPER_EIGHT",
      "views": 5189,
      "rank": 245
    },
    {
      "title": "R-指定_(ラッパー)",
      "views": 5182,
      "rank": 246
    },
    {
      "title": "御三卿",
      "views": 5180,
      "rank": 247
    },
    {
      "title": "孤独のグルメ",
      "views": 5168,
      "rank": 248
    },
    {
      "title": "黒木純",
      "views": 5161,
      "rank": 249
    },
    {
      "title": "BE：FIRST",
      "views": 5158,
      "rank": 250
    },
    {
      "title": "青島心_(モデル)",
      "views": 5156,
      "rank": 251
    },
    {
      "title": "特捜最前線",
      "views": 5151,
      "rank": 252
    },
    {
      "title": "頓知気さきな",
      "views": 5139,
      "rank": 253
    },
    {
      "title": "伊藤沙莉",
      "views": 5133,
      "rank": 254
    },
    {
      "title": "浜辺美波",
      "views": 5106,
      "rank": 255
    },
    {
      "title": "オッペンハイマー_(映画)",
      "views": 5106,
      "rank": 256
    },
    {
      "title": "向田邦子",
      "views": 5098,
      "rank": 257
    },
    {
      "title": "SMAP",
      "views": 5090,
      "rank": 258
    },
    {
      "title": "神木隆之介",
      "views": 5087,
      "rank": 259
    },
    {
      "title": "Timelesz",
      "views": 5081,
      "rank": 260
    },
    {
      "title": "イーロン・マスク",
      "views": 5072,
      "rank": 261
    },
    {
      "title": "佐倉綾音",
      "views": 5068,
      "rank": 262
    },
    {
      "title": "森千晴",
      "views": 5064,
      "rank": 263
    },
    {
      "title": "THE_ALFEE",
      "views": 5045,
      "rank": 264
    },
    {
      "title": "斎藤千和",
      "views": 5044,
      "rank": 265
    },
    {
      "title": "徳川忠長",
      "views": 5036,
      "rank": 266
    },
    {
      "title": "Da-iCE",
      "views": 5035,
      "rank": 267
    },
    {
      "title": "中山美穂",
      "views": 5033,
      "rank": 268
    },
    {
      "title": "ガクテンソク",
      "views": 5020,
      "rank": 269
    },
    {
      "title": "寺西拓人",
      "views": 5007,
      "rank": 270
    },
    {
      "title": "魔神英雄伝ワタルシリーズ",
      "views": 5004,
      "rank": 271
    },
    {
      "title": "市川雷蔵_(8代目)",
      "views": 4988,
      "rank": 272
    },
    {
      "title": "アンダーニンジャ",
      "views": 4985,
      "rank": 273
    },
    {
      "title": "若隆景渥",
      "views": 4983,
      "rank": 274
    },
    {
      "title": "炭谷銀仁朗",
      "views": 4978,
      "rank": 275
    },
    {
      "title": "松本潤",
      "views": 4958,
      "rank": 276
    },
    {
      "title": "沢尻エリカ",
      "views": 4950,
      "rank": 277
    },
    {
      "title": "NiziU",
      "views": 4939,
      "rank": 278
    },
    {
      "title": "ヒコロヒー",
      "views": 4935,
      "rank": 279
    },
    {
      "title": "神谷浩史",
      "views": 4923,
      "rank": 280
    },
    {
      "title": "舟越桂",
      "views": 4920,
      "rank": 281
    },
    {
      "title": "わたしの幸せな結婚",
      "views": 4916,
      "rank": 282
    },
    {
      "title": "桑田佳祐",
      "views": 4900,
      "rank": 283
    },
    {
      "title": "山本富士子",
      "views": 4895,
      "rank": 284
    },
    {
      "title": "藤井風",
      "views": 4878,
      "rank": 285
    },
    {
      "title": "わんだふるぷりきゅあ!",
      "views": 4852,
      "rank": 286
    },
    {
      "title": "Hey!_Say!_JUMP",
      "views": 4843,
      "rank": 287
    },
    {
      "title": "STARTO_ENTERTAINMENT",
      "views": 4839,
      "rank": 288
    },
    {
      "title": "葵わかな",
      "views": 4836,
      "rank": 289
    },
    {
      "title": "なすなかにし",
      "views": 4817,
      "rank": 290
    },
    {
      "title": "仮面ライダーガヴ",
      "views": 4811,
      "rank": 291
    },
    {
      "title": "たぬかな",
      "views": 4805,
      "rank": 292
    },
    {
      "title": "坂井澄江",
      "views": 4802,
      "rank": 293
    },
    {
      "title": "あきない世傳_金と銀",
      "views": 4764,
      "rank": 294
    },
    {
      "title": "ATARU",
      "views": 4755,
      "rank": 295
    },
    {
      "title": "ドクターX〜外科医・大門未知子〜",
      "views": 4753,
      "rank": 296
    },
    {
      "title": "バカリズム",
      "views": 4745,
      "rank": 297
    },
    {
      "title": "乃木坂46",
      "views": 4727,
      "rank": 298
    },
    {
      "title": "はたらく細胞",
      "views": 4696,
      "rank": 299
    },
    {
      "title": "阿武咲奎也",
      "views": 4693,
      "rank": 300
    }
  ]
}
